astrocabtools/all_tools/src/__init__.py
astrocabtools/all_tools/src/all_tools.py
astrocabtools/all_tools/src/ui/__init__.py
astrocabtools/all_tools/src/ui/all_tools.ui
astrocabtools/all_tools/src/ui/ui_all_tools.py
astrocabtools/cube_ans/src/__init__.py
astrocabtools/cube_ans/src/main.py
astrocabtools/cube_ans/src/io/__init__.py
astrocabtools/cube_ans/src/io/megara_cube_load.py
astrocabtools/cube_ans/src/io/miri_cube_load.py
astrocabtools/cube_ans/src/io/muse_cube_load.py
astrocabtools/cube_ans/src/models/__init__.py
astrocabtools/cube_ans/src/models/ellipseSelection.py
astrocabtools/cube_ans/src/models/globalStats.py
astrocabtools/cube_ans/src/models/rectangleSelection.py
astrocabtools/cube_ans/src/models/rectangleSpectrum.py
astrocabtools/cube_ans/src/ui/__init__.py
astrocabtools/cube_ans/src/ui/backgroundSubtraction.ui
astrocabtools/cube_ans/src/ui/cubeSelection.ui
astrocabtools/cube_ans/src/ui/cube_ans.ui
astrocabtools/cube_ans/src/ui/ellipseCoordinates.ui
astrocabtools/cube_ans/src/ui/ellipseCreation.ui
astrocabtools/cube_ans/src/ui/rectangleCoordinates.ui
astrocabtools/cube_ans/src/ui/rectangleCreation.ui
astrocabtools/cube_ans/src/ui/spectrumParametersSelection.ui
astrocabtools/cube_ans/src/ui/spectrumVisualization.ui
astrocabtools/cube_ans/src/ui/ui_backgroundSubtraction.py
astrocabtools/cube_ans/src/ui/ui_cubeSelection.py
astrocabtools/cube_ans/src/ui/ui_cube_ans.py
astrocabtools/cube_ans/src/ui/ui_ellipseCoordinates.py
astrocabtools/cube_ans/src/ui/ui_ellipseCreation.py
astrocabtools/cube_ans/src/ui/ui_rectangleCoordinates.py
astrocabtools/cube_ans/src/ui/ui_rectangleCreation.py
astrocabtools/cube_ans/src/ui/ui_spectrumParametersSelection.py
astrocabtools/cube_ans/src/ui/ui_spectrumVisualization.py
astrocabtools/cube_ans/src/ui/ui_wavelengthRangeSelection.py
astrocabtools/cube_ans/src/ui/wavelengthRangeSelection.ui
astrocabtools/cube_ans/src/utils/__init__.py
astrocabtools/cube_ans/src/utils/aperture_operations.py
AstroCabTools-1.5.1.dist-info/LICENSE
AstroCabTools-1.5.1.dist-info/METADATA
AstroCabTools-1.5.1.dist-info/WHEEL
AstroCabTools-1.5.1.dist-info/entry_points.txt
AstroCabTools-1.5.1.dist-info/top_level.txt
AstroCabTools-1.5.1.dist-info/RECORD
