Metadata-Version: 2.1
Name: AstroCabTools
Version: 1.5.1
Summary: Set of analysis tools of MRS data
Home-page: UNKNOWN
Author: Alejandro Gorgues
License: UNKNOWN
Platform: UNKNOWN
Classifier: Programming Language :: Python :: 3.7
Requires-Python: >=3.7
Requires-Dist: matplotlib (>=3.1.3)
Requires-Dist: astropy (>=4.0)
Requires-Dist: PyQt5 (==5.14)
Requires-Dist: numpy (>=1.18.1)
Requires-Dist: seaborn (>=0.9.0)
Requires-Dist: lmfit (>=1.0.0)
Requires-Dist: PyPubSub (>=4.0.3)
Requires-Dist: photutils (<1.2>=1.1.0)
Requires-Dist: jwst (>=1.3.2)
